bunnyclient/__init__.py
bunnyclient/config/__init__.py
bunnyclient/config/connection.py
bunnyclient/config/environ.py
bunnyclient/handlers/__init__.py
bunnyclient/handlers/base.py
bunnyclient/utils.py
bunnyclient-0.1.0.dist-info/WHEEL
bunnyclient-0.1.0.dist-info/METADATA
bunnyclient-0.1.0.dist-info/RECORD
