Metadata-Version: 2.1
Name: bunnyclient
Version: 0.1.0
Summary: 
Author: Ramon Rodrigues
Author-email: ramon.srodrigues01@gmail.com
Requires-Python: >=3.8,<4.0
Classifier: Programming Language :: Python :: 3
Classifier: Programming Language :: Python :: 3.8
Classifier: Programming Language :: Python :: 3.9
Classifier: Programming Language :: Python :: 3.10
Requires-Dist: pika (>=1.2.0,<2.0.0)
Requires-Dist: prettyconf (>=2.2.1,<3.0.0)
Requires-Dist: pydantic (>=1.9.0,<2.0.0)
